[
	{
		"state": "0x0017",
		"type": "14",
		"multiple_state": false,
		"name": "<b>SET STUN<b>:",
		"last": "",
		"no_arg_text": "",
		"args": [
			{
				"index": 0,
				"prefix": "",
				"name": "type",
				"cls": "AirStunType",
				"type": "format_value",
				"range": false,
				"data": {

				}
			}
		]
	},
	{
		"state": "0x0021",
		"type": "14",
		"multiple_state": false,
		"name": "<b>SET TIRA PERSONA<b>:",
		"last": "",
		"no_arg_text": "",
		"args": [
			{
				"index": 0,
				"prefix": "",
				"name": "persona",
				"cls": "TiraPersona",
				"type": "format_value",
				"range": false,
				"data": {

				}
			}
		]
	},
	{
		"state": "0x0038",
		"type": "14",
		"multiple_state": false,
		"name": "<b>STOP TIME<b>:",
		"last": "",
		"no_arg_text": "",
		"args": [
			{
				"index": 0,
				"prefix": "",
				"name": "0",
				"cls": null,
				"type": "format_value",
				"range": false,
				"data": {

				}
			}
		]
	},
	{
		"state": "0x003e",
		"type": "14",
		"multiple_state": false,
		"name": "<b>FREEZE OPPONENT<b>:",
		"last": "",
		"no_arg_text": "",
		"args": [
			{
				"index": 0,
				"prefix": "",
				"name": "freeze",
				"cls": "BoolFlag",
				"type": "format_value",
				"range": false,
				"data": {
					"replace_char": ""
				}
			}
		]
	}
]
