[
	{
		"state": "0x0005",
		"type": "01",
		"multiple_state": false,
		"name": "BUTTON INPUT",
		"last": "BUTTON INPUT CHECK",
		"no_arg_text": "",
		"args": [
			{
				"index": -1,
				"prefix": "",
				"name": "",
				"cls": "InputType",
				"type": "name_from_enum",
				"data": {
					"replace_char": " ",
					"format": false,
					"slice": true,
					"slice_index": 0
				}
			},
			{
				"index": 0,
				"prefix": "",
				"name": "",
				"type": "format_value",
				"range": false,
				"cls": "PaddedButton",
				"data": {
					"replace_char": "+"
				}
			}
		]
	},
	{
		"state": "0x0006",
		"type": "01",
		"multiple_state": false,
		"name": "BUTTON INPUT",
		"last": "BUTTON INPUT CHECK",
		"no_arg_text": "",
		"args": [
			{
				"index": -1,
				"prefix": "",
				"name": "",
				"cls": "InputType",
				"type": "name_from_enum",
				"data": {
					"replace_char": " ",
					"format": false,
					"slice": true,
					"slice_index": 0
				}
			},
			{
				"index": 0,
				"prefix": "",
				"name": "",
				"type": "format_value",
				"range": false,
				"cls": "PaddedButton",
				"data": {
					"replace_char": "+"
				}
			}
		]
	},
	{
		"state": "0x0020",
		"type": "01",
		"multiple_state": false,
		"name": "BUTTON INPUT",
		"last": "BUTTON INPUT CHECK",
		"no_arg_text": "",
		"args": [
			{
				"index": -1,
				"prefix": "",
				"name": "",
				"cls": "InputType",
				"type": "name_from_enum",
				"data": {
					"replace_char": " ",
					"format": false,
					"slice": true,
					"slice_index": 1
				}
			},
			{
				"index": 0,
				"prefix": "",
				"name": "",
				"type": "format_value",
				"range": false,
				"cls": "PaddedButton",
				"data": {
					"replace_char": "+"
				}
			},
			{
				"index": 1,
				"prefix": "",
				"name": "",
				"type": "format_value",
				"range": false,
				"cls": null,
				"data": {
					"prefix": "for ",
					"suffix": " frames"
				}
			}
		]
	},
	{
		"state": "0x0009",
		"type": "01",
		"multiple_state": false,
		"name": "LAST ANIMATION FRAME",
		"last": "LAST ANIMATION FRAME CHECK",
		"no_arg_text": "",
		"args": [

		]
	},
	{
		"state": "0x000b",
		"type": "01",
		"multiple_state": false,
		"name": "SPECIAL STATE",
		"last": "SPECIAL STATE CHECK",
		"no_arg_text": "",
		"args": [
			{
				"index": 0,
				"prefix": "",
				"name": "state",
				"cls": "SpecialState",
				"type": "format_value",
				"range": false,
				"data": {

				}
			}
		]
	},
	{
		"state": "0x000e",
		"type": "01",
		"multiple_state": false,
		"name": "ARRIVED FROM MOVE",
		"last": "ARRIVED FROM CHECK",
		"no_arg_text": "",
		"args": [
			{
				"index": 0,
				"prefix": "",
				"name": "move_id",
				"cls": null,
				"type": "format_value",
				"range": false,
				"data": {
					"decode": true
				}
			}
		]
	},
	{
		"state": "0x0011",
		"type": "01",
		"multiple_state": false,
		"name": "PLAYER CHARACTER",
		"last": "PLAYER CHARACTER CHECK",
		"no_arg_text": "",
		"args": [
			{
				"index": 0,
				"prefix": "",
				"name": "character",
				"cls": "CharacterID",
				"type": "format_value",
				"range": false,
				"data": {

				}
			}
		]
	},
	{
		"state": "0x0014",
		"type": "01",
		"multiple_state": false,
		"name": "OPPONENT DISTANCE",
		"last": "OPPONENT DISTANCE CHECK",
		"no_arg_text": "",
		"args": [
			{
				"index": 0,
				"prefix": "",
				"name": "0",
				"cls": null,
				"type": "format_value",
				"range": false,
				"data": {

				}
			},
			{
				"index": 1,
				"prefix": "",
				"name": "1",
				"cls": null,
				"type": "format_value",
				"range": false,
				"data": {
					"decode": true
				}
			}
		]
	},
	{
		"state": "0x008a",
		"type": "01",
		"multiple_state": false,
		"name": "OPPONENT STYLE",
		"last": "OPPONENT STYLE CHECK",
		"no_arg_text": "",
		"args": [
			{
				"index": 0,
				"prefix": "",
				"name": "style",
				"cls": "CharacterID",
				"type": "format_value",
				"range": false,
				"data": {

				}
			}
		]
	},
	{
		"state": "0x008f",
		"type": "01",
		"multiple_state": false,
		"name": "SWITCHING TO MOVE",
		"last": "SWITCH CHECK",
		"no_arg_text": "",
		"args": [
			{
				"index": 0,
				"prefix": "",
				"name": "0",
				"cls": null,
				"type": "format_value",
				"range": false,
				"data": {

				}
			},
			{
				"index": 1,
				"prefix": "",
				"name": "move_id",
				"cls": null,
				"type": "format_value",
				"range": false,
				"data": {
					"decode": true
				}
			}
		]
	},
	{
		"state": "0x0010",
		"type": "01",
		"multiple_state": false,
		"name": "FIRST RUN",
		"last": "FIRST RUN CHECK",
		"no_arg_text": "",
		"args": [

		]
	},
	{
		"state": "0x0016",
		"type": "01",
		"multiple_state": false,
		"name": "ROUND OVER",
		"last": "ROUND OVER CHECK",
		"no_arg_text": "",
		"args": [

		]
	},
	{
		"state": "0x0022",
		"type": "01",
		"multiple_state": false,
		"name": "CHARACTER STATE VALUE",
		"last": "CHARACTER STATE VALUE CHECK",
		"no_arg_text": "",
		"args": [
			{
				"index": 0,
				"prefix": "",
				"name": "state",
				"cls": "CharacterState",
				"type": "format_value",
				"range": false,
				"data": {

				}
			},
			{
				"index": 1,
				"prefix": "",
				"name": "value",
				"cls": null,
				"type": "format_value",
				"range": false,
				"data": {

				}
			}
		]
	},
	{
		"state": "0x0035",
		"type": "01",
		"multiple_state": false,
		"name": "COUNTER HIT",
		"last": "COUNTER HIT CHECK",
		"no_arg_text": "",
		"args": [

		]
	},
	{
		"state": "0x003c",
		"type": "01",
		"multiple_state": false,
		"name": "OPPONENT CHARACTER",
		"last": "OPPONENT CHARACTER CHECK",
		"no_arg_text": "",
		"args": [
			{
				"index": 0,
				"prefix": "",
				"name": "character",
				"cls": "CharacterID",
				"type": "format_value",
				"range": false,
				"data": {

				}
			}
		]
	},
	{
		"state": "0x0054",
		"type": "01",
		"multiple_state": false,
		"name": "EXITING MOVE",
		"last": "EXITING MOVE CHECK",
		"no_arg_text": "",
		"args": [

		]
	},
	{
		"state": "0x005a",
		"type": "01",
		"multiple_state": false,
		"name": "OPPONENT GENDER",
		"last": "OPPONENT GENDER CHECK",
		"no_arg_text": "",
		"args": [
			{
				"index": 0,
				"prefix": "",
				"name": "gender",
				"cls": "CharacterGender",
				"type": "format_value",
				"range": false,
				"data": {

				}
			}
		]
	},
	{
		"state": "0x0061",
		"type": "01",
		"multiple_state": false,
		"name": "OPPONENT STATE",
		"last": "OPPONENT STATE CHECK",
		"no_arg_text": "",
		"args": [
			{
				"index": 0,
				"prefix": "",
				"name": "state",
				"cls": "OpponentState",
				"type": "format_value",
				"range": false,
				"data": {

				}
			}
		]
	},
	{
		"state": "0x0066",
		"type": "01",
		"multiple_state": false,
		"name": "OPPONENT STATE",
		"last": "OPPONENT STATE CHECK",
		"no_arg_text": "",
		"args": [
			{
				"index": 0,
				"prefix": "",
				"name": "state",
				"cls": "OpponentState",
				"type": "format_value",
				"range": false,
				"data": {

				}
			}
		]
	},
	{
		"state": "0x006b",
		"type": "01",
		"multiple_state": false,
		"name": "PLAYER STYLE",
		"last": "PLAYER STYLE CHECK",
		"no_arg_text": "",
		"args": [
			{
				"index": 0,
				"prefix": "",
				"name": "style",
				"cls": "CharacterID",
				"type": "format_value",
				"range": false,
				"data": {

				}
			}
		]
	},
	{
		"state": "0x0075",
		"type": "01",
		"multiple_state": false,
		"name": "WEAPON VARIATION",
		"last": "WEAPON VARIATION CHECK",
		"no_arg_text": "",
		"args": [
			{
				"index": 0,
				"prefix": "",
				"name": "variation",
				"cls": null,
				"type": "format_value",
				"range": false,
				"data": {

				}
			}
		]
	},
	{
		"state": "0x007b",
		"type": "01",
		"multiple_state": false,
		"name": "PLAYER HP PERCENT",
		"last": "PLAYER HP PERCENT CHECK",
		"no_arg_text": "",
		"args": [
			{
				"index": 0,
				"prefix": "",
				"name": "value",
				"cls": null,
				"type": "format_value",
				"range": false,
				"data": {
					"prefix": "below ",
					"suffix": "%"
				}
			}
		]
	},
	{
		"state": "0x007f",
		"type": "01",
		"multiple_state": false,
		"name": "CHANCE OF RETURNING TRUE",
		"last": "RETURN TRUE % CHECK",
		"no_arg_text": "",
		"args": [
			{
				"index": 0,
				"prefix": "",
				"name": "percentage",
				"cls": null,
				"type": "format_value",
				"range": false,
				"data": {
					"suffix": "%"
				}
			}
		]
	},
	{
		"state": "0x009c",
		"type": "01",
		"multiple_state": false,
		"name": "PLAYER DISTANCE",
		"last": "PLAYER DISTANCE CHECK",
		"no_arg_text": "",
		"args": [
			{
				"index": 0,
				"prefix": "",
				"name": "0",
				"cls": null,
				"type": "format_value",
				"range": false,
				"data": {

				}
			},
			{
				"index": 1,
				"prefix": "",
				"name": "1",
				"cls": null,
				"type": "format_value",
				"range": false,
				"data": {

				}
			}
		]
	},
	{
		"state": "0x138a",
		"type": "01",
		"multiple_state": false,
		"name": "PLAYER CHARACTER VALUE",
		"last": "PLAYER CHARACTER VALUE CHECK",
		"no_arg_text": "",
		"args": [
			{
				"index": 0,
				"prefix": "",
				"name": "target_value",
				"cls": "CharacterValue",
				"type": "format_value",
				"range": false,
				"data": {

				}
			},
			{
				"index": [
					1,
					2
				],
				"name": "value",
				"cls": null,
				"type": "format_value",
				"range": true,
				"data": {
					"negative": true
				}
			}
		]
	},
	{
		"state": [
			"0x13ae",
			"0x13af",
			"0x0024"
		],
		"type": "01",
		"multiple_state": true,
		"name": "DIRECTION INPUT",
		"last": "DIRECTION INPUT CHECK",
		"no_arg_text": "",
		"args": [
			{
				"index": 0,
				"prefix": "",
				"name": "",
				"cls": "PaddedButton",
				"type": "format_value",
				"range": false,
				"data": {
					"slice": true
				}
			}
		]
	},
	{
		"state": "0x13bd",
		"type": "01",
		"multiple_state": false,
		"name": "OPPONENT HP PERCENT",
		"last": "OPPONENT HP PERCENT CHECK",
		"no_arg_text": "",
		"args": [
			{
				"index": 0,
				"prefix": "",
				"name": "value",
				"cls": null,
				"type": "format_value",
				"range": false,
				"data": {
					"prefix": "below ",
					"suffix": "%"
				}
			}
		]
	},
	{
		"state": "0x13c5",
		"type": "01",
		"multiple_state": false,
		"name": "PLAYER CHARACTER (MIMIC)",
		"last": "PLAYER CHARACTER CHECK",
		"no_arg_text": "",
		"args": [
			{
				"index": 0,
				"prefix": "",
				"name": "character",
				"cls": "CharacterID",
				"type": "format_value",
				"range": false,
				"data": {

				}
			}
		]
	},
	{
		"state": "0x13ce",
		"type": "01",
		"multiple_state": false,
		"name": "OPPONENT CHARACTER VALUE",
		"last": "OPPONENT CHARACTER VALUE CHECK",
		"no_arg_text": "",
		"args": [
			{
				"index": 0,
				"prefix": "",
				"name": "target_value",
				"cls": "CharacterValue",
				"type": "format_value",
				"range": false,
				"data": {

				}
			},
			{
				"index": [
					1,
					2
				],
				"name": "value",
				"cls": null,
				"type": "format_value",
				"range": true,
				"data": {
					"negative": true
				}
			}
		]
	},
	{
		"state": "0x13da",
		"type": "01",
		"multiple_state": false,
		"name": "TRAINING MODE",
		"last": "TRAINING MODE CHECK",
		"no_arg_text": "",
		"args": [

		]
	}
]
